irisml/azureml/__init__.py
irisml/azureml/azureml.py
irisml/commands/cancel_aml.py
irisml/commands/run_aml.py
irisml/tasks/run_azureml_child.py
irisml_tasks_azureml-1.0.4.dist-info/LICENSE
irisml_tasks_azureml-1.0.4.dist-info/METADATA
irisml_tasks_azureml-1.0.4.dist-info/WHEEL
irisml_tasks_azureml-1.0.4.dist-info/entry_points.txt
irisml_tasks_azureml-1.0.4.dist-info/top_level.txt
irisml_tasks_azureml-1.0.4.dist-info/RECORD
