Metadata-Version: 2.1
Name: irisml-tasks-azureml
Version: 1.0.4
Summary: Utility tools to use IrisML on AzureML
Home-page: https://github.com/microsoft/irisml-tasks-azureml
Author: irisdev
License: MIT
Requires-Python: >=3.8
License-File: LICENSE
Requires-Dist: azure-ai-ml <2
Requires-Dist: azure-identity <2
Requires-Dist: irisml
